CacheSys/__init__.py
CacheSys-0.0.7.dist-info/LICENSE.txt
CacheSys-0.0.7.dist-info/METADATA
CacheSys-0.0.7.dist-info/WHEEL
CacheSys-0.0.7.dist-info/top_level.txt
CacheSys-0.0.7.dist-info/RECORD
